{
    "channel": {
        "title": "XML Historical Foreign Exchange Rates for Australian Dollar (AUD) (7 Sep 2022)",
        "link": "http://www.floatrates.com/currency/aud/",
        "xmlLink": "http://www.floatrates.com/daily/aud.xml",
        "description": "XML historical foreign exchange rates for Australian Dollar (AUD) from the Float Rates. Published at 7 Sep 2022.",
        "language": "en",
        "baseCurrency": "AUD",
        "pubDate": "Wed, 7 Sep 2022",
        "lastBuildDate": "Wed, 7 Sep 2022",
        "item": [
            {
                "title": "1 AUD = 0.677826 EUR",
                "link": "http://www.floatrates.com/aud/eur/",
                "description": "1 Australian Dollar = 0.677826 Euro",
                "pubDate": null,
                "baseCurrency": "AUD",
                "baseName": "Australian Dollar",
                "targetCurrency": "EUR",
                "targetName": "Euro",
                "exchangeRate": "0.677826",
                "inverseRate": "1.475305",
                "inverseDescription": "1 Euro = 1.475305 Australian Dollar"
            },
            {
                "title": "1 AUD = 0.671825 USD",
                "link": "http://www.floatrates.com/aud/usd/",
                "description": "1 Australian Dollar = 0.671825 U.S. Dollar",
                "pubDate": null,
                "baseCurrency": "AUD",
                "baseName": "Australian Dollar",
                "targetCurrency": "USD",
                "targetName": "U.S. Dollar",
                "exchangeRate": "0.671825",
                "inverseRate": "1.488483",
                "inverseDescription": "1 U.S. Dollar = 1.488483 Australian Dollar"
            },
            {
                "title": "1 AUD = 0.885223 CAD",
                "link": "http://www.floatrates.com/aud/cad/",
                "description": "1 Australian Dollar = 0.885223 Canadian Dollar",
                "pubDate": null,
                "baseCurrency": "AUD",
                "baseName": "Australian Dollar",
                "targetCurrency": "CAD",
                "targetName": "Canadian Dollar",
                "exchangeRate": "0.885223",
                "inverseRate": "1.129659",
                "inverseDescription": "1 Canadian Dollar = 1.129659 Australian Dollar"
            },
            {
                "title": "1 AUD = 0.585494 GBP",
                "link": "http://www.floatrates.com/aud/gbp/",
                "description": "1 Australian Dollar = 0.585494 U.K. Pound Sterling",
                "pubDate": null,
                "baseCurrency": "AUD",
                "baseName": "Australian Dollar",
                "targetCurrency": "GBP",
                "targetName": "U.K. Pound Sterling",
                "exchangeRate": "0.585494",
                "inverseRate": "1.707961",
                "inverseDescription": "1 U.K. Pound Sterling = 1.707961 Australian Dollar"
            },
            {
                "title": "1 AUD = 0.584473 GIP",
                "link": "http://www.floatrates.com/aud/gip/",
                "description": "1 Australian Dollar = 0.584473 Gibraltar pound",
                "pubDate": null,
                "baseCurrency": "AUD",
                "baseName": "Australian Dollar",
                "targetCurrency": "GIP",
                "targetName": "Gibraltar pound",
                "exchangeRate": "0.584473",
                "inverseRate": "1.710943",
                "inverseDescription": "1 Gibraltar pound = 1.710943 Australian Dollar"
            },
            {
                "title": "1 AUD = 0.660795 CHF",
                "link": "http://www.floatrates.com/aud/chf/",
                "description": "1 Australian Dollar = 0.660795 Swiss Franc",
                "pubDate": null,
                "baseCurrency": "AUD",
                "baseName": "Australian Dollar",
                "targetCurrency": "CHF",
                "targetName": "Swiss Franc",
                "exchangeRate": "0.660795",
                "inverseRate": "1.513328",
                "inverseDescription": "1 Swiss Franc = 1.513328 Australian Dollar"
            },
            {
                "title": "1 AUD = 5.051911 DKK",
                "link": "http://www.floatrates.com/aud/dkk/",
                "description": "1 Australian Dollar = 5.051911 Danish Krone",
                "pubDate": null,
                "baseCurrency": "AUD",
                "baseName": "Australian Dollar",
                "targetCurrency": "DKK",
                "targetName": "Danish Krone",
                "exchangeRate": "5.051911",
                "inverseRate": "0.197945",
                "inverseDescription": "1 Danish Krone = 0.197945 Australian Dollar"
            },
            {
                "title": "1 AUD = 7.238577 SEK",
                "link": "http://www.floatrates.com/aud/sek/",
                "description": "1 Australian Dollar = 7.238577 Swedish Krona",
                "pubDate": null,
                "baseCurrency": "AUD",
                "baseName": "Australian Dollar",
                "targetCurrency": "SEK",
                "targetName": "Swedish Krona",
                "exchangeRate": "7.238577",
                "inverseRate": "0.138149",
                "inverseDescription": "1 Swedish Krona = 0.138149 Australian Dollar"
            },
            {
                "title": "1 AUD = 6.747519 NOK",
                "link": "http://www.floatrates.com/aud/nok/",
                "description": "1 Australian Dollar = 6.747519 Norwegian Krone",
                "pubDate": null,
                "baseCurrency": "AUD",
                "baseName": "Australian Dollar",
                "targetCurrency": "NOK",
                "targetName": "Norwegian Krone",
                "exchangeRate": "6.747519",
                "inverseRate": "0.148203",
                "inverseDescription": "1 Norwegian Krone = 0.148203 Australian Dollar"
            },
            {
                "title": "1 AUD = 2.524875 SAR",
                "link": "http://www.floatrates.com/aud/sar/",
                "description": "1 Australian Dollar = 2.524875 Saudi Riyal",
                "pubDate": null,
                "baseCurrency": "AUD",
                "baseName": "Australian Dollar",
                "targetCurrency": "SAR",
                "targetName": "Saudi Riyal",
                "exchangeRate": "2.524875",
                "inverseRate": "0.396059",
                "inverseDescription": "1 Saudi Riyal = 0.396059 Australian Dollar"
            },
            {
                "title": "1 AUD = 0.207524 KWD",
                "link": "http://www.floatrates.com/aud/kwd/",
                "description": "1 Australian Dollar = 0.207524 Kuwaiti Dinar",
                "pubDate": null,
                "baseCurrency": "AUD",
                "baseName": "Australian Dollar",
                "targetCurrency": "KWD",
                "targetName": "Kuwaiti Dinar",
                "exchangeRate": "0.207524",
                "inverseRate": "4.818724",
                "inverseDescription": "1 Kuwaiti Dinar = 4.818724 Australian Dollar"
            },
            {
                "title": "1 AUD = 2.468658 AED",
                "link": "http://www.floatrates.com/aud/aed/",
                "description": "1 Australian Dollar = 2.468658 U.A.E Dirham",
                "pubDate": null,
                "baseCurrency": "AUD",
                "baseName": "Australian Dollar",
                "targetCurrency": "AED",
                "targetName": "U.A.E Dirham",
                "exchangeRate": "2.468658",
                "inverseRate": "0.405078",
                "inverseDescription": "1 U.A.E Dirham = 0.405078 Australian Dollar"
            },
            {
                "title": "1 AUD = 2.467588 QAR",
                "link": "http://www.floatrates.com/aud/qar/",
                "description": "1 Australian Dollar = 2.467588 Qatari Rial",
                "pubDate": null,
                "baseCurrency": "AUD",
                "baseName": "Australian Dollar",
                "targetCurrency": "QAR",
                "targetName": "Qatari Rial",
                "exchangeRate": "2.467588",
                "inverseRate": "0.405254",
                "inverseDescription": "1 Qatari Rial = 0.405254 Australian Dollar"
            },
            {
                "title": "1 AUD = 0.253208 BHD",
                "link": "http://www.floatrates.com/aud/bhd/",
                "description": "1 Australian Dollar = 0.253208 Bahrain Dinar",
                "pubDate": null,
                "baseCurrency": "AUD",
                "baseName": "Australian Dollar",
                "targetCurrency": "BHD",
                "targetName": "Bahrain Dinar",
                "exchangeRate": "0.253208",
                "inverseRate": "3.949329",
                "inverseDescription": "1 Bahrain Dinar = 3.949329 Australian Dollar"
            },
            {
                "title": "1 AUD = 96.935787 JPY",
                "link": "http://www.floatrates.com/aud/jpy/",
                "description": "1 Australian Dollar = 96.935787 Japanese Yen",
                "pubDate": null,
                "baseCurrency": "AUD",
                "baseName": "Australian Dollar",
                "targetCurrency": "JPY",
                "targetName": "Japanese Yen",
                "exchangeRate": "96.935787",
                "inverseRate": "0.010316",
                "inverseDescription": "1 Japanese Yen = 0.010316 Australian Dollar"
            },
            {
                "title": "1 AUD = 94.395715 DZD",
                "link": "http://www.floatrates.com/aud/dzd/",
                "description": "1 Australian Dollar = 94.395715 Algerian Dinar",
                "pubDate": null,
                "baseCurrency": "AUD",
                "baseName": "Australian Dollar",
                "targetCurrency": "DZD",
                "targetName": "Algerian Dinar",
                "exchangeRate": "94.395715",
                "inverseRate": "0.010594",
                "inverseDescription": "1 Algerian Dinar = 0.010594 Australian Dollar"
            },
            {
                "title": "1 AUD = 2.167773 TND",
                "link": "http://www.floatrates.com/aud/tnd/",
                "description": "1 Australian Dollar = 2.167773 Tunisian Dinar",
                "pubDate": null,
                "baseCurrency": "AUD",
                "baseName": "Australian Dollar",
                "targetCurrency": "TND",
                "targetName": "Tunisian Dinar",
                "exchangeRate": "2.167773",
                "inverseRate": "0.461303",
                "inverseDescription": "1 Tunisian Dinar = 0.461303 Australian Dollar"
            },
            {
                "title": "1 AUD = 3.325008 LYD",
                "link": "http://www.floatrates.com/aud/lyd/",
                "description": "1 Australian Dollar = 3.325008 Libyan Dinar",
                "pubDate": null,
                "baseCurrency": "AUD",
                "baseName": "Australian Dollar",
                "targetCurrency": "LYD",
                "targetName": "Libyan Dinar",
                "exchangeRate": "3.325008",
                "inverseRate": "0.300751",
                "inverseDescription": "1 Libyan Dinar = 0.300751 Australian Dollar"
            },
            {
                "title": "1 AUD = 25.337841 MRO",
                "link": "http://www.floatrates.com/aud/mro/",
                "description": "1 Australian Dollar = 25.337841 Mauritanian Ouguiya",
                "pubDate": null,
                "baseCurrency": "AUD",
                "baseName": "Australian Dollar",
                "targetCurrency": "MRO",
                "targetName": "Mauritanian Ouguiya",
                "exchangeRate": "25.337841",
                "inverseRate": "0.039467",
                "inverseDescription": "1 Mauritanian Ouguiya = 0.039467 Australian Dollar"
            },
            {
                "title": "1 AUD = 0.258887 OMR",
                "link": "http://www.floatrates.com/aud/omr/",
                "description": "1 Australian Dollar = 0.258887 Omani Rial",
                "pubDate": null,
                "baseCurrency": "AUD",
                "baseName": "Australian Dollar",
                "targetCurrency": "OMR",
                "targetName": "Omani Rial",
                "exchangeRate": "0.258887",
                "inverseRate": "3.862685",
                "inverseDescription": "1 Omani Rial = 3.862685 Australian Dollar"
            },
            {
                "title": "1 AUD = 3.523727 BRL",
                "link": "http://www.floatrates.com/aud/brl/",
                "description": "1 Australian Dollar = 3.523727 Brazilian Real",
                "pubDate": null,
                "baseCurrency": "AUD",
                "baseName": "Australian Dollar",
                "targetCurrency": "BRL",
                "targetName": "Brazilian Real",
                "exchangeRate": "3.523727",
                "inverseRate": "0.283790",
                "inverseDescription": "1 Brazilian Real = 0.283790 Australian Dollar"
            },
            {
                "title": "1 AUD = 42.668953 RUB",
                "link": "http://www.floatrates.com/aud/rub/",
                "description": "1 Australian Dollar = 42.668953 Russian Rouble",
                "pubDate": null,
                "baseCurrency": "AUD",
                "baseName": "Australian Dollar",
                "targetCurrency": "RUB",
                "targetName": "Russian Rouble",
                "exchangeRate": "42.668953",
                "inverseRate": "0.023436",
                "inverseDescription": "1 Russian Rouble = 0.023436 Australian Dollar"
            },
            {
                "title": "1 AUD = 53.666217 INR",
                "link": "http://www.floatrates.com/aud/inr/",
                "description": "1 Australian Dollar = 53.666217 Indian Rupee",
                "pubDate": null,
                "baseCurrency": "AUD",
                "baseName": "Australian Dollar",
                "targetCurrency": "INR",
                "targetName": "Indian Rupee",
                "exchangeRate": "53.666217",
                "inverseRate": "0.018634",
                "inverseDescription": "1 Indian Rupee = 0.018634 Australian Dollar"
            },
            {
                "title": "1 AUD = 4.683427 CNY",
                "link": "http://www.floatrates.com/aud/cny/",
                "description": "1 Australian Dollar = 4.683427 Chinese Yuan",
                "pubDate": null,
                "baseCurrency": "AUD",
                "baseName": "Australian Dollar",
                "targetCurrency": "CNY",
                "targetName": "Chinese Yuan",
                "exchangeRate": "4.683427",
                "inverseRate": "0.213519",
                "inverseDescription": "1 Chinese Yuan = 0.213519 Australian Dollar"
            },
            {
                "title": "1 AUD = 1.000000 AUD",
                "link": "http://www.floatrates.com/aud/aud/",
                "description": "1 Australian Dollar = 1.000000 Australian Dollar",
                "pubDate": null,
                "baseCurrency": "AUD",
                "baseName": "Australian Dollar",
                "targetCurrency": "AUD",
                "targetName": "Australian Dollar",
                "exchangeRate": "1.000000",
                "inverseRate": "1.000000",
                "inverseDescription": "1 Australian Dollar = 1.000000 Australian Dollar"
            },
            {
                "title": "1 AUD = 11.677364 ZAR",
                "link": "http://www.floatrates.com/aud/zar/",
                "description": "1 Australian Dollar = 11.677364 South African Rand",
                "pubDate": null,
                "baseCurrency": "AUD",
                "baseName": "Australian Dollar",
                "targetCurrency": "ZAR",
                "targetName": "South African Rand",
                "exchangeRate": "11.677364",
                "inverseRate": "0.085636",
                "inverseDescription": "1 South African Rand = 0.085636 Australian Dollar"
            },
            {
                "title": "1 AUD = 12.249908 TRY",
                "link": "http://www.floatrates.com/aud/try/",
                "description": "1 Australian Dollar = 12.249908 Turkish Lira",
                "pubDate": null,
                "baseCurrency": "AUD",
                "baseName": "Australian Dollar",
                "targetCurrency": "TRY",
                "targetName": "Turkish Lira",
                "exchangeRate": "12.249908",
                "inverseRate": "0.081633",
                "inverseDescription": "1 Turkish Lira = 0.081633 Australian Dollar"
            },
            {
                "title": "1 AUD = 12.932243 EGP",
                "link": "http://www.floatrates.com/aud/egp/",
                "description": "1 Australian Dollar = 12.932243 Egyptian Pound",
                "pubDate": null,
                "baseCurrency": "AUD",
                "baseName": "Australian Dollar",
                "targetCurrency": "EGP",
                "targetName": "Egyptian Pound",
                "exchangeRate": "12.932243",
                "inverseRate": "0.077326",
                "inverseDescription": "1 Egyptian Pound = 0.077326 Australian Dollar"
            },
            {
                "title": "1 AUD = 0.476915 JOD",
                "link": "http://www.floatrates.com/aud/jod/",
                "description": "1 Australian Dollar = 0.476915 Jordanian Dinar",
                "pubDate": null,
                "baseCurrency": "AUD",
                "baseName": "Australian Dollar",
                "targetCurrency": "JOD",
                "targetName": "Jordanian Dinar",
                "exchangeRate": "0.476915",
                "inverseRate": "2.096812",
                "inverseDescription": "1 Jordanian Dinar = 2.096812 Australian Dollar"
            },
            {
                "title": "1 AUD = 446.788484 XOF",
                "link": "http://www.floatrates.com/aud/xof/",
                "description": "1 Australian Dollar = 446.788484 West African CFA Franc",
                "pubDate": null,
                "baseCurrency": "AUD",
                "baseName": "Australian Dollar",
                "targetCurrency": "XOF",
                "targetName": "West African CFA Franc",
                "exchangeRate": "446.788484",
                "inverseRate": "0.002238",
                "inverseDescription": "1 West African CFA Franc = 0.002238 Australian Dollar"
            },
            {
                "title": "1 AUD = 7.143728 MAD",
                "link": "http://www.floatrates.com/aud/mad/",
                "description": "1 Australian Dollar = 7.143728 Moroccan Dirham",
                "pubDate": null,
                "baseCurrency": "AUD",
                "baseName": "Australian Dollar",
                "targetCurrency": "MAD",
                "targetName": "Moroccan Dirham",
                "exchangeRate": "7.143728",
                "inverseRate": "0.139983",
                "inverseDescription": "1 Moroccan Dirham = 0.139983 Australian Dollar"
            },
            {
                "title": "1 AUD = 1.207774 ANG",
                "link": "http://www.floatrates.com/aud/ang/",
                "description": "1 Australian Dollar = 1.207774 Neth. Antillean Guilder",
                "pubDate": null,
                "baseCurrency": "AUD",
                "baseName": "Australian Dollar",
                "targetCurrency": "ANG",
                "targetName": "Neth. Antillean Guilder",
                "exchangeRate": "1.207774",
                "inverseRate": "0.827969",
                "inverseDescription": "1 Neth. Antillean Guilder = 0.827969 Australian Dollar"
            },
            {
                "title": "1 AUD = 5.273638 HKD",
                "link": "http://www.floatrates.com/aud/hkd/",
                "description": "1 Australian Dollar = 5.273638 Hong Kong Dollar",
                "pubDate": null,
                "baseCurrency": "AUD",
                "baseName": "Australian Dollar",
                "targetCurrency": "HKD",
                "targetName": "Hong Kong Dollar",
                "exchangeRate": "5.273638",
                "inverseRate": "0.189622",
                "inverseDescription": "1 Hong Kong Dollar = 0.189622 Australian Dollar"
            },
            {
                "title": "1 AUD = 242.734721 LKR",
                "link": "http://www.floatrates.com/aud/lkr/",
                "description": "1 Australian Dollar = 242.734721 Sri Lanka Rupee",
                "pubDate": null,
                "baseCurrency": "AUD",
                "baseName": "Australian Dollar",
                "targetCurrency": "LKR",
                "targetName": "Sri Lanka Rupee",
                "exchangeRate": "242.734721",
                "inverseRate": "0.004120",
                "inverseDescription": "1 Sri Lanka Rupee = 0.004120 Australian Dollar"
            },
            {
                "title": "1 AUD = 1.115813 NZD",
                "link": "http://www.floatrates.com/aud/nzd/",
                "description": "1 Australian Dollar = 1.115813 New Zealand Dollar",
                "pubDate": null,
                "baseCurrency": "AUD",
                "baseName": "Australian Dollar",
                "targetCurrency": "NZD",
                "targetName": "New Zealand Dollar",
                "exchangeRate": "1.115813",
                "inverseRate": "0.896207",
                "inverseDescription": "1 New Zealand Dollar = 0.896207 Australian Dollar"
            },
            {
                "title": "1 AUD = 149.563471 PKR",
                "link": "http://www.floatrates.com/aud/pkr/",
                "description": "1 Australian Dollar = 149.563471 Pakistani Rupee",
                "pubDate": null,
                "baseCurrency": "AUD",
                "baseName": "Australian Dollar",
                "targetCurrency": "PKR",
                "targetName": "Pakistani Rupee",
                "exchangeRate": "149.563471",
                "inverseRate": "0.006686",
                "inverseDescription": "1 Pakistani Rupee = 0.006686 Australian Dollar"
            },
            {
                "title": "1 AUD = 0.946194 SGD",
                "link": "http://www.floatrates.com/aud/sgd/",
                "description": "1 Australian Dollar = 0.946194 Singapore Dollar",
                "pubDate": null,
                "baseCurrency": "AUD",
                "baseName": "Australian Dollar",
                "targetCurrency": "SGD",
                "targetName": "Singapore Dollar",
                "exchangeRate": "0.946194",
                "inverseRate": "1.056865",
                "inverseDescription": "1 Singapore Dollar = 1.056865 Australian Dollar"
            },
            {
                "title": "1 AUD = 63.869075 BDT",
                "link": "http://www.floatrates.com/aud/bdt/",
                "description": "1 Australian Dollar = 63.869075 Bangladeshi taka",
                "pubDate": null,
                "baseCurrency": "AUD",
                "baseName": "Australian Dollar",
                "targetCurrency": "BDT",
                "targetName": "Bangladeshi taka",
                "exchangeRate": "63.869075",
                "inverseRate": "0.015657",
                "inverseDescription": "1 Bangladeshi taka = 0.015657 Australian Dollar"
            },
            {
                "title": "1 AUD = 10,040.395854 IDR",
                "link": "http://www.floatrates.com/aud/idr/",
                "description": "1 Australian Dollar = 10,040.395854 Indonesian Rupiah",
                "pubDate": null,
                "baseCurrency": "AUD",
                "baseName": "Australian Dollar",
                "targetCurrency": "IDR",
                "targetName": "Indonesian Rupiah",
                "exchangeRate": "10,040.395854",
                "inverseRate": "0.000100",
                "inverseDescription": "1 Indonesian Rupiah = 0.000100 Australian Dollar"
            },
            {
                "title": "1 AUD = 1,015.389028 LBP",
                "link": "http://www.floatrates.com/aud/lbp/",
                "description": "1 Australian Dollar = 1,015.389028 Lebanese Pound",
                "pubDate": null,
                "baseCurrency": "AUD",
                "baseName": "Australian Dollar",
                "targetCurrency": "LBP",
                "targetName": "Lebanese Pound",
                "exchangeRate": "1,015.389028",
                "inverseRate": "0.000985",
                "inverseDescription": "1 Lebanese Pound = 0.000985 Australian Dollar"
            },
            {
                "title": "1 AUD = 85.906727 NPR",
                "link": "http://www.floatrates.com/aud/npr/",
                "description": "1 Australian Dollar = 85.906727 Nepalese Rupee",
                "pubDate": null,
                "baseCurrency": "AUD",
                "baseName": "Australian Dollar",
                "targetCurrency": "NPR",
                "targetName": "Nepalese Rupee",
                "exchangeRate": "85.906727",
                "inverseRate": "0.011641",
                "inverseDescription": "1 Nepalese Rupee = 0.011641 Australian Dollar"
            },
            {
                "title": "1 AUD = 38.412769 PHP",
                "link": "http://www.floatrates.com/aud/php/",
                "description": "1 Australian Dollar = 38.412769 Philippine Peso",
                "pubDate": null,
                "baseCurrency": "AUD",
                "baseName": "Australian Dollar",
                "targetCurrency": "PHP",
                "targetName": "Philippine Peso",
                "exchangeRate": "38.412769",
                "inverseRate": "0.026033",
                "inverseDescription": "1 Philippine Peso = 0.026033 Australian Dollar"
            },
            {
                "title": "1 AUD = 24.674683 THB",
                "link": "http://www.floatrates.com/aud/thb/",
                "description": "1 Australian Dollar = 24.674683 Thai Baht",
                "pubDate": null,
                "baseCurrency": "AUD",
                "baseName": "Australian Dollar",
                "targetCurrency": "THB",
                "targetName": "Thai Baht",
                "exchangeRate": "24.674683",
                "inverseRate": "0.040527",
                "inverseDescription": "1 Thai Baht = 0.040527 Australian Dollar"
            },
            {
                "title": "1 AUD = 2.312150 ILS",
                "link": "http://www.floatrates.com/aud/ils/",
                "description": "1 Australian Dollar = 2.312150 Israeli New Sheqel",
                "pubDate": null,
                "baseCurrency": "AUD",
                "baseName": "Australian Dollar",
                "targetCurrency": "ILS",
                "targetName": "Israeli New Sheqel",
                "exchangeRate": "2.312150",
                "inverseRate": "0.432498",
                "inverseDescription": "1 Israeli New Sheqel = 0.432498 Australian Dollar"
            },
            {
                "title": "1 AUD = 930.660333 KRW",
                "link": "http://www.floatrates.com/aud/krw/",
                "description": "1 Australian Dollar = 930.660333 South Korean Won",
                "pubDate": null,
                "baseCurrency": "AUD",
                "baseName": "Australian Dollar",
                "targetCurrency": "KRW",
                "targetName": "South Korean Won",
                "exchangeRate": "930.660333",
                "inverseRate": "0.001075",
                "inverseDescription": "1 South Korean Won = 0.001075 Australian Dollar"
            },
            {
                "title": "1 AUD = 3.024484 MYR",
                "link": "http://www.floatrates.com/aud/myr/",
                "description": "1 Australian Dollar = 3.024484 Malaysian Ringgit",
                "pubDate": null,
                "baseCurrency": "AUD",
                "baseName": "Australian Dollar",
                "targetCurrency": "MYR",
                "targetName": "Malaysian Ringgit",
                "exchangeRate": "3.024484",
                "inverseRate": "0.330635",
                "inverseDescription": "1 Malaysian Ringgit = 0.330635 Australian Dollar"
            },
            {
                "title": "1 AUD = 20.759247 TWD",
                "link": "http://www.floatrates.com/aud/twd/",
                "description": "1 Australian Dollar = 20.759247 New Taiwan Dollar",
                "pubDate": null,
                "baseCurrency": "AUD",
                "baseName": "Australian Dollar",
                "targetCurrency": "TWD",
                "targetName": "New Taiwan Dollar",
                "exchangeRate": "20.759247",
                "inverseRate": "0.048171",
                "inverseDescription": "1 New Taiwan Dollar  = 0.048171 Australian Dollar"
            },
            {
                "title": "1 AUD = 15,850.712680 VND",
                "link": "http://www.floatrates.com/aud/vnd/",
                "description": "1 Australian Dollar = 15,850.712680 Vietnamese Dong",
                "pubDate": null,
                "baseCurrency": "AUD",
                "baseName": "Australian Dollar",
                "targetCurrency": "VND",
                "targetName": "Vietnamese Dong",
                "exchangeRate": "15,850.712680",
                "inverseRate": "0.000063",
                "inverseDescription": "1 Vietnamese Dong = 0.000063 Australian Dollar"
            },
            {
                "title": "1 AUD = 273.002497 HUF",
                "link": "http://www.floatrates.com/aud/huf/",
                "description": "1 Australian Dollar = 273.002497 Hungarian Forint",
                "pubDate": null,
                "baseCurrency": "AUD",
                "baseName": "Australian Dollar",
                "targetCurrency": "HUF",
                "targetName": "Hungarian Forint",
                "exchangeRate": "273.002497",
                "inverseRate": "0.003663",
                "inverseDescription": "1 Hungarian Forint = 0.003663 Australian Dollar"
            },
            {
                "title": "1 AUD = 24.915548 UAH",
                "link": "http://www.floatrates.com/aud/uah/",
                "description": "1 Australian Dollar = 24.915548 Ukrainian Hryvnia",
                "pubDate": null,
                "baseCurrency": "AUD",
                "baseName": "Australian Dollar",
                "targetCurrency": "UAH",
                "targetName": "Ukrainian Hryvnia",
                "exchangeRate": "24.915548",
                "inverseRate": "0.040136",
                "inverseDescription": "1 Ukrainian Hryvnia = 0.040136 Australian Dollar"
            },
            {
                "title": "1 AUD = 16.734142 CZK",
                "link": "http://www.floatrates.com/aud/czk/",
                "description": "1 Australian Dollar = 16.734142 Czech Koruna",
                "pubDate": null,
                "baseCurrency": "AUD",
                "baseName": "Australian Dollar",
                "targetCurrency": "CZK",
                "targetName": "Czech Koruna",
                "exchangeRate": "16.734142",
                "inverseRate": "0.059758",
                "inverseDescription": "1 Czech Koruna = 0.059758 Australian Dollar"
            },
            {
                "title": "1 AUD = 96.028455 ISK",
                "link": "http://www.floatrates.com/aud/isk/",
                "description": "1 Australian Dollar = 96.028455 Icelandic Krona",
                "pubDate": null,
                "baseCurrency": "AUD",
                "baseName": "Australian Dollar",
                "targetCurrency": "ISK",
                "targetName": "Icelandic Krona",
                "exchangeRate": "96.028455",
                "inverseRate": "0.010414",
                "inverseDescription": "1 Icelandic Krona = 0.010414 Australian Dollar"
            },
            {
                "title": "1 AUD = 5.105289 HRK",
                "link": "http://www.floatrates.com/aud/hrk/",
                "description": "1 Australian Dollar = 5.105289 Croatian Kuna",
                "pubDate": null,
                "baseCurrency": "AUD",
                "baseName": "Australian Dollar",
                "targetCurrency": "HRK",
                "targetName": "Croatian Kuna",
                "exchangeRate": "5.105289",
                "inverseRate": "0.195875",
                "inverseDescription": "1 Croatian Kuna = 0.195875 Australian Dollar"
            },
            {
                "title": "1 AUD = 3.301079 RON",
                "link": "http://www.floatrates.com/aud/ron/",
                "description": "1 Australian Dollar = 3.301079 Romanian New Leu",
                "pubDate": null,
                "baseCurrency": "AUD",
                "baseName": "Australian Dollar",
                "targetCurrency": "RON",
                "targetName": "Romanian New Leu",
                "exchangeRate": "3.301079",
                "inverseRate": "0.302931",
                "inverseDescription": "1 Romanian New Leu = 0.302931 Australian Dollar"
            },
            {
                "title": "1 AUD = 1.328856 BGN",
                "link": "http://www.floatrates.com/aud/bgn/",
                "description": "1 Australian Dollar = 1.328856 Bulgarian Lev",
                "pubDate": null,
                "baseCurrency": "AUD",
                "baseName": "Australian Dollar",
                "targetCurrency": "BGN",
                "targetName": "Bulgarian Lev",
                "exchangeRate": "1.328856",
                "inverseRate": "0.752527",
                "inverseDescription": "1 Bulgarian Lev = 0.752527 Australian Dollar"
            },
            {
                "title": "1 AUD = 599.415292 CLP",
                "link": "http://www.floatrates.com/aud/clp/",
                "description": "1 Australian Dollar = 599.415292 Chilean Peso",
                "pubDate": null,
                "baseCurrency": "AUD",
                "baseName": "Australian Dollar",
                "targetCurrency": "CLP",
                "targetName": "Chilean Peso",
                "exchangeRate": "599.415292",
                "inverseRate": "0.001668",
                "inverseDescription": "1 Chilean Peso = 0.001668 Australian Dollar"
            },
            {
                "title": "1 AUD = 13.496645 MXN",
                "link": "http://www.floatrates.com/aud/mxn/",
                "description": "1 Australian Dollar = 13.496645 Mexican Peso",
                "pubDate": null,
                "baseCurrency": "AUD",
                "baseName": "Australian Dollar",
                "targetCurrency": "MXN",
                "targetName": "Mexican Peso",
                "exchangeRate": "13.496645",
                "inverseRate": "0.074092",
                "inverseDescription": "1 Mexican Peso = 0.074092 Australian Dollar"
            },
            {
                "title": "1 AUD = 59.484409 AFN",
                "link": "http://www.floatrates.com/aud/afn/",
                "description": "1 Australian Dollar = 59.484409 Afghan afghani",
                "pubDate": null,
                "baseCurrency": "AUD",
                "baseName": "Australian Dollar",
                "targetCurrency": "AFN",
                "targetName": "Afghan afghani",
                "exchangeRate": "59.484409",
                "inverseRate": "0.016811",
                "inverseDescription": "1 Afghan afghani = 0.016811 Australian Dollar"
            },
            {
                "title": "1 AUD = 2,834.052392 MGA",
                "link": "http://www.floatrates.com/aud/mga/",
                "description": "1 Australian Dollar = 2,834.052392 Malagasy ariary",
                "pubDate": null,
                "baseCurrency": "AUD",
                "baseName": "Australian Dollar",
                "targetCurrency": "MGA",
                "targetName": "Malagasy ariary",
                "exchangeRate": "2,834.052392",
                "inverseRate": "0.000353",
                "inverseDescription": "1 Malagasy ariary = 0.000353 Australian Dollar"
            },
            {
                "title": "1 AUD = 0.671825 PAB",
                "link": "http://www.floatrates.com/aud/pab/",
                "description": "1 Australian Dollar = 0.671825 Panamanian Balboa",
                "pubDate": null,
                "baseCurrency": "AUD",
                "baseName": "Australian Dollar",
                "targetCurrency": "PAB",
                "targetName": "Panamanian Balboa",
                "exchangeRate": "0.671825",
                "inverseRate": "1.488483",
                "inverseDescription": "1 Panamanian Balboa = 1.488483 Australian Dollar"
            },
            {
                "title": "1 AUD = 35.520123 ETB",
                "link": "http://www.floatrates.com/aud/etb/",
                "description": "1 Australian Dollar = 35.520123 Ethiopian birr",
                "pubDate": null,
                "baseCurrency": "AUD",
                "baseName": "Australian Dollar",
                "targetCurrency": "ETB",
                "targetName": "Ethiopian birr",
                "exchangeRate": "35.520123",
                "inverseRate": "0.028153",
                "inverseDescription": "1 Ethiopian birr = 0.028153 Australian Dollar"
            },
            {
                "title": "1 AUD = 5.356303 VES",
                "link": "http://www.floatrates.com/aud/ves/",
                "description": "1 Australian Dollar = 5.356303 Venezuelan Bolivar",
                "pubDate": null,
                "baseCurrency": "AUD",
                "baseName": "Australian Dollar",
                "targetCurrency": "VES",
                "targetName": "Venezuelan Bolivar",
                "exchangeRate": "5.356303",
                "inverseRate": "0.186696",
                "inverseDescription": "1 Venezuelan Bolivar = 0.186696 Australian Dollar"
            },
            {
                "title": "1 AUD = 4.656023 BOB",
                "link": "http://www.floatrates.com/aud/bob/",
                "description": "1 Australian Dollar = 4.656023 Bolivian Boliviano",
                "pubDate": null,
                "baseCurrency": "AUD",
                "baseName": "Australian Dollar",
                "targetCurrency": "BOB",
                "targetName": "Bolivian Boliviano",
                "exchangeRate": "4.656023",
                "inverseRate": "0.214776",
                "inverseDescription": "1 Bolivian Boliviano = 0.214776 Australian Dollar"
            },
            {
                "title": "1 AUD = 441.136487 CRC",
                "link": "http://www.floatrates.com/aud/crc/",
                "description": "1 Australian Dollar = 441.136487 Costa Rican Col\u00f3n",
                "pubDate": null,
                "baseCurrency": "AUD",
                "baseName": "Australian Dollar",
                "targetCurrency": "CRC",
                "targetName": "Costa Rican Col\u00f3n",
                "exchangeRate": "441.136487",
                "inverseRate": "0.002267",
                "inverseDescription": "1 Costa Rican Col\u00f3n = 0.002267 Australian Dollar"
            },
            {
                "title": "1 AUD = 5.892739 SVC",
                "link": "http://www.floatrates.com/aud/svc/",
                "description": "1 Australian Dollar = 5.892739 Salvadoran colon",
                "pubDate": null,
                "baseCurrency": "AUD",
                "baseName": "Australian Dollar",
                "targetCurrency": "SVC",
                "targetName": "Salvadoran colon",
                "exchangeRate": "5.892739",
                "inverseRate": "0.169700",
                "inverseDescription": "1 Salvadoran colon = 0.169700 Australian Dollar"
            },
            {
                "title": "1 AUD = 24.181627 NIO",
                "link": "http://www.floatrates.com/aud/nio/",
                "description": "1 Australian Dollar = 24.181627 Nicaraguan C\u00f3rdoba",
                "pubDate": null,
                "baseCurrency": "AUD",
                "baseName": "Australian Dollar",
                "targetCurrency": "NIO",
                "targetName": "Nicaraguan C\u00f3rdoba",
                "exchangeRate": "24.181627",
                "inverseRate": "0.041354",
                "inverseDescription": "1 Nicaraguan C\u00f3rdoba = 0.041354 Australian Dollar"
            },
            {
                "title": "1 AUD = 37.477270 GMD",
                "link": "http://www.floatrates.com/aud/gmd/",
                "description": "1 Australian Dollar = 37.477270 Gambian dalasi",
                "pubDate": null,
                "baseCurrency": "AUD",
                "baseName": "Australian Dollar",
                "targetCurrency": "GMD",
                "targetName": "Gambian dalasi",
                "exchangeRate": "37.477270",
                "inverseRate": "0.026683",
                "inverseDescription": "1 Gambian dalasi = 0.026683 Australian Dollar"
            },
            {
                "title": "1 AUD = 41.953452 MKD",
                "link": "http://www.floatrates.com/aud/mkd/",
                "description": "1 Australian Dollar = 41.953452 Macedonian denar",
                "pubDate": null,
                "baseCurrency": "AUD",
                "baseName": "Australian Dollar",
                "targetCurrency": "MKD",
                "targetName": "Macedonian denar",
                "exchangeRate": "41.953452",
                "inverseRate": "0.023836",
                "inverseDescription": "1 Macedonian denar = 0.023836 Australian Dollar"
            },
            {
                "title": "1 AUD = 981.644354 IQD",
                "link": "http://www.floatrates.com/aud/iqd/",
                "description": "1 Australian Dollar = 981.644354 Iraqi dinar",
                "pubDate": null,
                "baseCurrency": "AUD",
                "baseName": "Australian Dollar",
                "targetCurrency": "IQD",
                "targetName": "Iraqi dinar",
                "exchangeRate": "981.644354",
                "inverseRate": "0.001019",
                "inverseDescription": "1 Iraqi dinar = 0.001019 Australian Dollar"
            },
            {
                "title": "1 AUD = 79.305657 RSD",
                "link": "http://www.floatrates.com/aud/rsd/",
                "description": "1 Australian Dollar = 79.305657 Serbian Dinar",
                "pubDate": null,
                "baseCurrency": "AUD",
                "baseName": "Australian Dollar",
                "targetCurrency": "RSD",
                "targetName": "Serbian Dinar",
                "exchangeRate": "79.305657",
                "inverseRate": "0.012609",
                "inverseDescription": "1 Serbian Dinar = 0.012609 Australian Dollar"
            },
            {
                "title": "1 AUD = 16.781161 STN",
                "link": "http://www.floatrates.com/aud/stn/",
                "description": "1 Australian Dollar = 16.781161 S\u00e3o Tom\u00e9 and Pr\u00edncipe Dobra",
                "pubDate": null,
                "baseCurrency": "AUD",
                "baseName": "Australian Dollar",
                "targetCurrency": "STN",
                "targetName": "S\u00e3o Tom\u00e9 and Pr\u00edncipe Dobra",
                "exchangeRate": "16.781161",
                "inverseRate": "0.059591",
                "inverseDescription": "1 S\u00e3o Tom\u00e9 and Pr\u00edncipe Dobra = 0.059591 Australian Dollar"
            },
            {
                "title": "1 AUD = 0.671825 BSD",
                "link": "http://www.floatrates.com/aud/bsd/",
                "description": "1 Australian Dollar = 0.671825 Bahamian Dollar",
                "pubDate": null,
                "baseCurrency": "AUD",
                "baseName": "Australian Dollar",
                "targetCurrency": "BSD",
                "targetName": "Bahamian Dollar",
                "exchangeRate": "0.671825",
                "inverseRate": "1.488483",
                "inverseDescription": "1 Bahamian Dollar = 1.488483 Australian Dollar"
            },
            {
                "title": "1 AUD = 1.358957 BBD",
                "link": "http://www.floatrates.com/aud/bbd/",
                "description": "1 Australian Dollar = 1.358957 Barbadian Dollar",
                "pubDate": null,
                "baseCurrency": "AUD",
                "baseName": "Australian Dollar",
                "targetCurrency": "BBD",
                "targetName": "Barbadian Dollar",
                "exchangeRate": "1.358957",
                "inverseRate": "0.735858",
                "inverseDescription": "1 Barbadian Dollar = 0.735858 Australian Dollar"
            },
            {
                "title": "1 AUD = 1.356650 BZD",
                "link": "http://www.floatrates.com/aud/bzd/",
                "description": "1 Australian Dollar = 1.356650 Belize dollar",
                "pubDate": null,
                "baseCurrency": "AUD",
                "baseName": "Australian Dollar",
                "targetCurrency": "BZD",
                "targetName": "Belize dollar",
                "exchangeRate": "1.356650",
                "inverseRate": "0.737110",
                "inverseDescription": "1 Belize dollar = 0.737110 Australian Dollar"
            },
            {
                "title": "1 AUD = 0.947007 BND",
                "link": "http://www.floatrates.com/aud/bnd/",
                "description": "1 Australian Dollar = 0.947007 Brunei Dollar",
                "pubDate": null,
                "baseCurrency": "AUD",
                "baseName": "Australian Dollar",
                "targetCurrency": "BND",
                "targetName": "Brunei Dollar",
                "exchangeRate": "0.947007",
                "inverseRate": "1.055959",
                "inverseDescription": "1 Brunei Dollar = 1.055959 Australian Dollar"
            },
            {
                "title": "1 AUD = 1.509282 FJD",
                "link": "http://www.floatrates.com/aud/fjd/",
                "description": "1 Australian Dollar = 1.509282 Fiji Dollar",
                "pubDate": null,
                "baseCurrency": "AUD",
                "baseName": "Australian Dollar",
                "targetCurrency": "FJD",
                "targetName": "Fiji Dollar",
                "exchangeRate": "1.509282",
                "inverseRate": "0.662567",
                "inverseDescription": "1 Fiji Dollar = 0.662567 Australian Dollar"
            },
            {
                "title": "1 AUD = 140.810073 GYD",
                "link": "http://www.floatrates.com/aud/gyd/",
                "description": "1 Australian Dollar = 140.810073 Guyanese dollar",
                "pubDate": null,
                "baseCurrency": "AUD",
                "baseName": "Australian Dollar",
                "targetCurrency": "GYD",
                "targetName": "Guyanese dollar",
                "exchangeRate": "140.810073",
                "inverseRate": "0.007102",
                "inverseDescription": "1 Guyanese dollar = 0.007102 Australian Dollar"
            },
            {
                "title": "1 AUD = 100.845776 JMD",
                "link": "http://www.floatrates.com/aud/jmd/",
                "description": "1 Australian Dollar = 100.845776 Jamaican Dollar",
                "pubDate": null,
                "baseCurrency": "AUD",
                "baseName": "Australian Dollar",
                "targetCurrency": "JMD",
                "targetName": "Jamaican Dollar",
                "exchangeRate": "100.845776",
                "inverseRate": "0.009916",
                "inverseDescription": "1 Jamaican Dollar = 0.009916 Australian Dollar"
            },
            {
                "title": "1 AUD = 103.792568 LRD",
                "link": "http://www.floatrates.com/aud/lrd/",
                "description": "1 Australian Dollar = 103.792568 Liberian dollar",
                "pubDate": null,
                "baseCurrency": "AUD",
                "baseName": "Australian Dollar",
                "targetCurrency": "LRD",
                "targetName": "Liberian dollar",
                "exchangeRate": "103.792568",
                "inverseRate": "0.009635",
                "inverseDescription": "1 Liberian dollar = 0.009635 Australian Dollar"
            },
            {
                "title": "1 AUD = 11.641701 NAD",
                "link": "http://www.floatrates.com/aud/nad/",
                "description": "1 Australian Dollar = 11.641701 Namibian dollar",
                "pubDate": null,
                "baseCurrency": "AUD",
                "baseName": "Australian Dollar",
                "targetCurrency": "NAD",
                "targetName": "Namibian dollar",
                "exchangeRate": "11.641701",
                "inverseRate": "0.085898",
                "inverseDescription": "1 Namibian dollar = 0.085898 Australian Dollar"
            },
            {
                "title": "1 AUD = 17.516773 SRD",
                "link": "http://www.floatrates.com/aud/srd/",
                "description": "1 Australian Dollar = 17.516773 Surinamese dollar",
                "pubDate": null,
                "baseCurrency": "AUD",
                "baseName": "Australian Dollar",
                "targetCurrency": "SRD",
                "targetName": "Surinamese dollar",
                "exchangeRate": "17.516773",
                "inverseRate": "0.057088",
                "inverseDescription": "1 Surinamese dollar = 0.057088 Australian Dollar"
            },
            {
                "title": "1 AUD = 4.558407 TTD",
                "link": "http://www.floatrates.com/aud/ttd/",
                "description": "1 Australian Dollar = 4.558407 Trinidad Tobago Dollar",
                "pubDate": null,
                "baseCurrency": "AUD",
                "baseName": "Australian Dollar",
                "targetCurrency": "TTD",
                "targetName": "Trinidad Tobago Dollar",
                "exchangeRate": "4.558407",
                "inverseRate": "0.219375",
                "inverseDescription": "1 Trinidad Tobago Dollar = 0.219375 Australian Dollar"
            },
            {
                "title": "1 AUD = 1.824351 XCD",
                "link": "http://www.floatrates.com/aud/xcd/",
                "description": "1 Australian Dollar = 1.824351 East Caribbean Dollar",
                "pubDate": null,
                "baseCurrency": "AUD",
                "baseName": "Australian Dollar",
                "targetCurrency": "XCD",
                "targetName": "East Caribbean Dollar",
                "exchangeRate": "1.824351",
                "inverseRate": "0.548140",
                "inverseDescription": "1 East Caribbean Dollar = 0.548140 Australian Dollar"
            },
            {
                "title": "1 AUD = 5.530815 SBD",
                "link": "http://www.floatrates.com/aud/sbd/",
                "description": "1 Australian Dollar = 5.530815 Solomon Islands dollar",
                "pubDate": null,
                "baseCurrency": "AUD",
                "baseName": "Australian Dollar",
                "targetCurrency": "SBD",
                "targetName": "Solomon Islands dollar",
                "exchangeRate": "5.530815",
                "inverseRate": "0.180805",
                "inverseDescription": "1 Solomon Islands dollar = 0.180805 Australian Dollar"
            },
            {
                "title": "1 AUD = 272.292048 AMD",
                "link": "http://www.floatrates.com/aud/amd/",
                "description": "1 Australian Dollar = 272.292048 Armenia Dram",
                "pubDate": null,
                "baseCurrency": "AUD",
                "baseName": "Australian Dollar",
                "targetCurrency": "AMD",
                "targetName": "Armenia Dram",
                "exchangeRate": "272.292048",
                "inverseRate": "0.003673",
                "inverseDescription": "1 Armenia Dram = 0.003673 Australian Dollar"
            },
            {
                "title": "1 AUD = 75.042514 CVE",
                "link": "http://www.floatrates.com/aud/cve/",
                "description": "1 Australian Dollar = 75.042514 Cape Verde escudo",
                "pubDate": null,
                "baseCurrency": "AUD",
                "baseName": "Australian Dollar",
                "targetCurrency": "CVE",
                "targetName": "Cape Verde escudo",
                "exchangeRate": "75.042514",
                "inverseRate": "0.013326",
                "inverseDescription": "1 Cape Verde escudo = 0.013326 Australian Dollar"
            },
            {
                "title": "1 AUD = 1.218018 AWG",
                "link": "http://www.floatrates.com/aud/awg/",
                "description": "1 Australian Dollar = 1.218018 Aruban florin",
                "pubDate": null,
                "baseCurrency": "AUD",
                "baseName": "Australian Dollar",
                "targetCurrency": "AWG",
                "targetName": "Aruban florin",
                "exchangeRate": "1.218018",
                "inverseRate": "0.821006",
                "inverseDescription": "1 Aruban florin = 0.821006 Australian Dollar"
            },
            {
                "title": "1 AUD = 1,389.313819 BIF",
                "link": "http://www.floatrates.com/aud/bif/",
                "description": "1 Australian Dollar = 1,389.313819 Burundian franc",
                "pubDate": null,
                "baseCurrency": "AUD",
                "baseName": "Australian Dollar",
                "targetCurrency": "BIF",
                "targetName": "Burundian franc",
                "exchangeRate": "1,389.313819",
                "inverseRate": "0.000720",
                "inverseDescription": "1 Burundian franc = 0.000720 Australian Dollar"
            },
            {
                "title": "1 AUD = 446.233603 XAF",
                "link": "http://www.floatrates.com/aud/xaf/",
                "description": "1 Australian Dollar = 446.233603 Central African CFA Franc",
                "pubDate": null,
                "baseCurrency": "AUD",
                "baseName": "Australian Dollar",
                "targetCurrency": "XAF",
                "targetName": "Central African CFA Franc",
                "exchangeRate": "446.233603",
                "inverseRate": "0.002241",
                "inverseDescription": "1 Central African CFA Franc = 0.002241 Australian Dollar"
            },
            {
                "title": "1 AUD = 81.077661 XPF",
                "link": "http://www.floatrates.com/aud/xpf/",
                "description": "1 Australian Dollar = 81.077661 CFP Franc",
                "pubDate": null,
                "baseCurrency": "AUD",
                "baseName": "Australian Dollar",
                "targetCurrency": "XPF",
                "targetName": "CFP Franc",
                "exchangeRate": "81.077661",
                "inverseRate": "0.012334",
                "inverseDescription": "1 CFP Franc = 0.012334 Australian Dollar"
            },
            {
                "title": "1 AUD = 119.816015 DJF",
                "link": "http://www.floatrates.com/aud/djf/",
                "description": "1 Australian Dollar = 119.816015 Djiboutian franc",
                "pubDate": null,
                "baseCurrency": "AUD",
                "baseName": "Australian Dollar",
                "targetCurrency": "DJF",
                "targetName": "Djiboutian franc",
                "exchangeRate": "119.816015",
                "inverseRate": "0.008346",
                "inverseDescription": "1 Djiboutian franc = 0.008346 Australian Dollar"
            },
            {
                "title": "1 AUD = 5,812.383815 GNF",
                "link": "http://www.floatrates.com/aud/gnf/",
                "description": "1 Australian Dollar = 5,812.383815 Guinean franc",
                "pubDate": null,
                "baseCurrency": "AUD",
                "baseName": "Australian Dollar",
                "targetCurrency": "GNF",
                "targetName": "Guinean franc",
                "exchangeRate": "5,812.383815",
                "inverseRate": "0.000172",
                "inverseDescription": "1 Guinean franc = 0.000172 Australian Dollar"
            },
            {
                "title": "1 AUD = 334.219665 KMF",
                "link": "http://www.floatrates.com/aud/kmf/",
                "description": "1 Australian Dollar = 334.219665 \tComoro franc",
                "pubDate": null,
                "baseCurrency": "AUD",
                "baseName": "Australian Dollar",
                "targetCurrency": "KMF",
                "targetName": "Comoro franc",
                "exchangeRate": "334.219665",
                "inverseRate": "0.002992",
                "inverseDescription": "1 \tComoro franc = 0.002992 Australian Dollar"
            },
            {
                "title": "1 AUD = 1,382.703762 CDF",
                "link": "http://www.floatrates.com/aud/cdf/",
                "description": "1 Australian Dollar = 1,382.703762 Congolese franc",
                "pubDate": null,
                "baseCurrency": "AUD",
                "baseName": "Australian Dollar",
                "targetCurrency": "CDF",
                "targetName": "Congolese franc",
                "exchangeRate": "1,382.703762",
                "inverseRate": "0.000723",
                "inverseDescription": "1 Congolese franc = 0.000723 Australian Dollar"
            },
            {
                "title": "1 AUD = 696.169664 RWF",
                "link": "http://www.floatrates.com/aud/rwf/",
                "description": "1 Australian Dollar = 696.169664 Rwandan franc",
                "pubDate": null,
                "baseCurrency": "AUD",
                "baseName": "Australian Dollar",
                "targetCurrency": "RWF",
                "targetName": "Rwandan franc",
                "exchangeRate": "696.169664",
                "inverseRate": "0.001436",
                "inverseDescription": "1 Rwandan franc = 0.001436 Australian Dollar"
            },
            {
                "title": "1 AUD = 437.499808 SSP",
                "link": "http://www.floatrates.com/aud/ssp/",
                "description": "1 Australian Dollar = 437.499808 South Sudanese pound",
                "pubDate": null,
                "baseCurrency": "AUD",
                "baseName": "Australian Dollar",
                "targetCurrency": "SSP",
                "targetName": "South Sudanese pound",
                "exchangeRate": "437.499808",
                "inverseRate": "0.002286",
                "inverseDescription": "1 South Sudanese pound = 0.002286 Australian Dollar"
            },
            {
                "title": "1 AUD = 380.572750 SDG",
                "link": "http://www.floatrates.com/aud/sdg/",
                "description": "1 Australian Dollar = 380.572750 Sudanese pound",
                "pubDate": null,
                "baseCurrency": "AUD",
                "baseName": "Australian Dollar",
                "targetCurrency": "SDG",
                "targetName": "Sudanese pound",
                "exchangeRate": "380.572750",
                "inverseRate": "0.002628",
                "inverseDescription": "1 Sudanese pound = 0.002628 Australian Dollar"
            },
            {
                "title": "1 AUD = 1,682.532157 SYP",
                "link": "http://www.floatrates.com/aud/syp/",
                "description": "1 Australian Dollar = 1,682.532157 Syrian pound",
                "pubDate": null,
                "baseCurrency": "AUD",
                "baseName": "Australian Dollar",
                "targetCurrency": "SYP",
                "targetName": "Syrian pound",
                "exchangeRate": "1,682.532157",
                "inverseRate": "0.000594",
                "inverseDescription": "1 Syrian pound = 0.000594 Australian Dollar"
            },
            {
                "title": "1 AUD = 6.696295 GHS",
                "link": "http://www.floatrates.com/aud/ghs/",
                "description": "1 Australian Dollar = 6.696295 Ghanaian Cedi",
                "pubDate": null,
                "baseCurrency": "AUD",
                "baseName": "Australian Dollar",
                "targetCurrency": "GHS",
                "targetName": "Ghanaian Cedi",
                "exchangeRate": "6.696295",
                "inverseRate": "0.149336",
                "inverseDescription": "1 Ghanaian Cedi = 0.149336 Australian Dollar"
            },
            {
                "title": "1 AUD = 79.092505 HTG",
                "link": "http://www.floatrates.com/aud/htg/",
                "description": "1 Australian Dollar = 79.092505 Haitian gourde",
                "pubDate": null,
                "baseCurrency": "AUD",
                "baseName": "Australian Dollar",
                "targetCurrency": "HTG",
                "targetName": "Haitian gourde",
                "exchangeRate": "79.092505",
                "inverseRate": "0.012643",
                "inverseDescription": "1 Haitian gourde = 0.012643 Australian Dollar"
            },
            {
                "title": "1 AUD = 4,647.322580 PYG",
                "link": "http://www.floatrates.com/aud/pyg/",
                "description": "1 Australian Dollar = 4,647.322580 Paraguayan Guaran\u00ed",
                "pubDate": null,
                "baseCurrency": "AUD",
                "baseName": "Australian Dollar",
                "targetCurrency": "PYG",
                "targetName": "Paraguayan Guaran\u00ed",
                "exchangeRate": "4,647.322580",
                "inverseRate": "0.000215",
                "inverseDescription": "1 Paraguayan Guaran\u00ed = 0.000215 Australian Dollar"
            },
            {
                "title": "1 AUD = 2.371522 PGK",
                "link": "http://www.floatrates.com/aud/pgk/",
                "description": "1 Australian Dollar = 2.371522 Papua New Guinean kina",
                "pubDate": null,
                "baseCurrency": "AUD",
                "baseName": "Australian Dollar",
                "targetCurrency": "PGK",
                "targetName": "Papua New Guinean kina",
                "exchangeRate": "2.371522",
                "inverseRate": "0.421670",
                "inverseDescription": "1 Papua New Guinean kina = 0.421670 Australian Dollar"
            },
            {
                "title": "1 AUD = 10,585.467213 LAK",
                "link": "http://www.floatrates.com/aud/lak/",
                "description": "1 Australian Dollar = 10,585.467213 Lao kip",
                "pubDate": null,
                "baseCurrency": "AUD",
                "baseName": "Australian Dollar",
                "targetCurrency": "LAK",
                "targetName": "Lao kip",
                "exchangeRate": "10,585.467213",
                "inverseRate": "0.000094",
                "inverseDescription": "1 Lao kip = 0.000094 Australian Dollar"
            },
            {
                "title": "1 AUD = 691.351881 MWK",
                "link": "http://www.floatrates.com/aud/mwk/",
                "description": "1 Australian Dollar = 691.351881 Malawian kwacha",
                "pubDate": null,
                "baseCurrency": "AUD",
                "baseName": "Australian Dollar",
                "targetCurrency": "MWK",
                "targetName": "Malawian kwacha",
                "exchangeRate": "691.351881",
                "inverseRate": "0.001446",
                "inverseDescription": "1 Malawian kwacha = 0.001446 Australian Dollar"
            },
            {
                "title": "1 AUD = 10.382628 ZMW",
                "link": "http://www.floatrates.com/aud/zmw/",
                "description": "1 Australian Dollar = 10.382628 Zambian kwacha",
                "pubDate": null,
                "baseCurrency": "AUD",
                "baseName": "Australian Dollar",
                "targetCurrency": "ZMW",
                "targetName": "Zambian kwacha",
                "exchangeRate": "10.382628",
                "inverseRate": "0.096315",
                "inverseDescription": "1 Zambian kwacha = 0.096315 Australian Dollar"
            },
            {
                "title": "1 AUD = 288.001000 AOA",
                "link": "http://www.floatrates.com/aud/aoa/",
                "description": "1 Australian Dollar = 288.001000 Angolan kwanza",
                "pubDate": null,
                "baseCurrency": "AUD",
                "baseName": "Australian Dollar",
                "targetCurrency": "AOA",
                "targetName": "Angolan kwanza",
                "exchangeRate": "288.001000",
                "inverseRate": "0.003472",
                "inverseDescription": "1 Angolan kwanza = 0.003472 Australian Dollar"
            },
            {
                "title": "1 AUD = 1,413.267506 MMK",
                "link": "http://www.floatrates.com/aud/mmk/",
                "description": "1 Australian Dollar = 1,413.267506 Myanma Kyat",
                "pubDate": null,
                "baseCurrency": "AUD",
                "baseName": "Australian Dollar",
                "targetCurrency": "MMK",
                "targetName": "Myanma Kyat",
                "exchangeRate": "1,413.267506",
                "inverseRate": "0.000708",
                "inverseDescription": "1 Myanma Kyat = 0.000708 Australian Dollar"
            },
            {
                "title": "1 AUD = 1.941622 GEL",
                "link": "http://www.floatrates.com/aud/gel/",
                "description": "1 Australian Dollar = 1.941622 Georgian lari",
                "pubDate": null,
                "baseCurrency": "AUD",
                "baseName": "Australian Dollar",
                "targetCurrency": "GEL",
                "targetName": "Georgian lari",
                "exchangeRate": "1.941622",
                "inverseRate": "0.515033",
                "inverseDescription": "1 Georgian lari = 0.515033 Australian Dollar"
            },
            {
                "title": "1 AUD = 13.050061 MDL",
                "link": "http://www.floatrates.com/aud/mdl/",
                "description": "1 Australian Dollar = 13.050061 Moldova Lei",
                "pubDate": null,
                "baseCurrency": "AUD",
                "baseName": "Australian Dollar",
                "targetCurrency": "MDL",
                "targetName": "Moldova Lei",
                "exchangeRate": "13.050061",
                "inverseRate": "0.076628",
                "inverseDescription": "1 Moldova Lei = 0.076628 Australian Dollar"
            },
            {
                "title": "1 AUD = 79.790618 ALL",
                "link": "http://www.floatrates.com/aud/all/",
                "description": "1 Australian Dollar = 79.790618 Albanian lek",
                "pubDate": null,
                "baseCurrency": "AUD",
                "baseName": "Australian Dollar",
                "targetCurrency": "ALL",
                "targetName": "Albanian lek",
                "exchangeRate": "79.790618",
                "inverseRate": "0.012533",
                "inverseDescription": "1 Albanian lek = 0.012533 Australian Dollar"
            },
            {
                "title": "1 AUD = 16.589575 HNL",
                "link": "http://www.floatrates.com/aud/hnl/",
                "description": "1 Australian Dollar = 16.589575 Honduran Lempira",
                "pubDate": null,
                "baseCurrency": "AUD",
                "baseName": "Australian Dollar",
                "targetCurrency": "HNL",
                "targetName": "Honduran Lempira",
                "exchangeRate": "16.589575",
                "inverseRate": "0.060279",
                "inverseDescription": "1 Honduran Lempira = 0.060279 Australian Dollar"
            },
            {
                "title": "1 AUD = 11.641701 SZL",
                "link": "http://www.floatrates.com/aud/szl/",
                "description": "1 Australian Dollar = 11.641701 Swazi lilangeni",
                "pubDate": null,
                "baseCurrency": "AUD",
                "baseName": "Australian Dollar",
                "targetCurrency": "SZL",
                "targetName": "Swazi lilangeni",
                "exchangeRate": "11.641701",
                "inverseRate": "0.085898",
                "inverseDescription": "1 Swazi lilangeni = 0.085898 Australian Dollar"
            },
            {
                "title": "1 AUD = 11.637463 LSL",
                "link": "http://www.floatrates.com/aud/lsl/",
                "description": "1 Australian Dollar = 11.637463 Lesotho loti",
                "pubDate": null,
                "baseCurrency": "AUD",
                "baseName": "Australian Dollar",
                "targetCurrency": "LSL",
                "targetName": "Lesotho loti",
                "exchangeRate": "11.637463",
                "inverseRate": "0.085929",
                "inverseDescription": "1 Lesotho loti = 0.085929 Australian Dollar"
            },
            {
                "title": "1 AUD = 1.141565 AZN",
                "link": "http://www.floatrates.com/aud/azn/",
                "description": "1 Australian Dollar = 1.141565 Azerbaijan Manat",
                "pubDate": null,
                "baseCurrency": "AUD",
                "baseName": "Australian Dollar",
                "targetCurrency": "AZN",
                "targetName": "Azerbaijan Manat",
                "exchangeRate": "1.141565",
                "inverseRate": "0.875991",
                "inverseDescription": "1 Azerbaijan Manat = 0.875991 Australian Dollar"
            },
            {
                "title": "1 AUD = 43.141850 MZN",
                "link": "http://www.floatrates.com/aud/mzn/",
                "description": "1 Australian Dollar = 43.141850 Mozambican metical",
                "pubDate": null,
                "baseCurrency": "AUD",
                "baseName": "Australian Dollar",
                "targetCurrency": "MZN",
                "targetName": "Mozambican metical",
                "exchangeRate": "43.141850",
                "inverseRate": "0.023179",
                "inverseDescription": "1 Mozambican metical = 0.023179 Australian Dollar"
            },
            {
                "title": "1 AUD = 286.602927 NGN",
                "link": "http://www.floatrates.com/aud/ngn/",
                "description": "1 Australian Dollar = 286.602927 Nigerian Naira",
                "pubDate": null,
                "baseCurrency": "AUD",
                "baseName": "Australian Dollar",
                "targetCurrency": "NGN",
                "targetName": "Nigerian Naira",
                "exchangeRate": "286.602927",
                "inverseRate": "0.003489",
                "inverseDescription": "1 Nigerian Naira = 0.003489 Australian Dollar"
            },
            {
                "title": "1 AUD = 10.145386 ERN",
                "link": "http://www.floatrates.com/aud/ern/",
                "description": "1 Australian Dollar = 10.145386 Eritrean nakfa",
                "pubDate": null,
                "baseCurrency": "AUD",
                "baseName": "Australian Dollar",
                "targetCurrency": "ERN",
                "targetName": "Eritrean nakfa",
                "exchangeRate": "10.145386",
                "inverseRate": "0.098567",
                "inverseDescription": "1 Eritrean nakfa = 0.098567 Australian Dollar"
            },
            {
                "title": "1 AUD = 2.350643 TMT",
                "link": "http://www.floatrates.com/aud/tmt/",
                "description": "1 Australian Dollar = 2.350643 New Turkmenistan Manat",
                "pubDate": null,
                "baseCurrency": "AUD",
                "baseName": "Australian Dollar",
                "targetCurrency": "TMT",
                "targetName": "New Turkmenistan Manat",
                "exchangeRate": "2.350643",
                "inverseRate": "0.425416",
                "inverseDescription": "1 New Turkmenistan Manat = 0.425416 Australian Dollar"
            },
            {
                "title": "1 AUD = 25.411853 MRU",
                "link": "http://www.floatrates.com/aud/mru/",
                "description": "1 Australian Dollar = 25.411853 Mauritanian ouguiya",
                "pubDate": null,
                "baseCurrency": "AUD",
                "baseName": "Australian Dollar",
                "targetCurrency": "MRU",
                "targetName": "Mauritanian ouguiya",
                "exchangeRate": "25.411853",
                "inverseRate": "0.039352",
                "inverseDescription": "1 Mauritanian ouguiya = 0.039352 Australian Dollar"
            },
            {
                "title": "1 AUD = 1.593784 TOP",
                "link": "http://www.floatrates.com/aud/top/",
                "description": "1 Australian Dollar = 1.593784 Tongan pa\u02bbanga",
                "pubDate": null,
                "baseCurrency": "AUD",
                "baseName": "Australian Dollar",
                "targetCurrency": "TOP",
                "targetName": "Tongan pa\u02bbanga",
                "exchangeRate": "1.593784",
                "inverseRate": "0.627438",
                "inverseDescription": "1 Tongan pa\u02bbanga = 0.627438 Australian Dollar"
            },
            {
                "title": "1 AUD = 5.444161 MOP",
                "link": "http://www.floatrates.com/aud/mop/",
                "description": "1 Australian Dollar = 5.444161 Macanese pataca",
                "pubDate": null,
                "baseCurrency": "AUD",
                "baseName": "Australian Dollar",
                "targetCurrency": "MOP",
                "targetName": "Macanese pataca",
                "exchangeRate": "5.444161",
                "inverseRate": "0.183683",
                "inverseDescription": "1 Macanese pataca = 0.183683 Australian Dollar"
            },
            {
                "title": "1 AUD = 94.581647 ARS",
                "link": "http://www.floatrates.com/aud/ars/",
                "description": "1 Australian Dollar = 94.581647 Argentine Peso",
                "pubDate": null,
                "baseCurrency": "AUD",
                "baseName": "Australian Dollar",
                "targetCurrency": "ARS",
                "targetName": "Argentine Peso",
                "exchangeRate": "94.581647",
                "inverseRate": "0.010573",
                "inverseDescription": "1 Argentine Peso = 0.010573 Australian Dollar"
            },
            {
                "title": "1 AUD = 35.602206 DOP",
                "link": "http://www.floatrates.com/aud/dop/",
                "description": "1 Australian Dollar = 35.602206 Dominican Peso",
                "pubDate": null,
                "baseCurrency": "AUD",
                "baseName": "Australian Dollar",
                "targetCurrency": "DOP",
                "targetName": "Dominican Peso",
                "exchangeRate": "35.602206",
                "inverseRate": "0.028088",
                "inverseDescription": "1 Dominican Peso = 0.028088 Australian Dollar"
            },
            {
                "title": "1 AUD = 3,010.263794 COP",
                "link": "http://www.floatrates.com/aud/cop/",
                "description": "1 Australian Dollar = 3,010.263794 Colombian Peso",
                "pubDate": null,
                "baseCurrency": "AUD",
                "baseName": "Australian Dollar",
                "targetCurrency": "COP",
                "targetName": "Colombian Peso",
                "exchangeRate": "3,010.263794",
                "inverseRate": "0.000332",
                "inverseDescription": "1 Colombian Peso = 0.000332 Australian Dollar"
            },
            {
                "title": "1 AUD = 0.671825 CUP",
                "link": "http://www.floatrates.com/aud/cup/",
                "description": "1 Australian Dollar = 0.671825 Cuban peso",
                "pubDate": null,
                "baseCurrency": "AUD",
                "baseName": "Australian Dollar",
                "targetCurrency": "CUP",
                "targetName": "Cuban peso",
                "exchangeRate": "0.671825",
                "inverseRate": "1.488483",
                "inverseDescription": "1 Cuban peso = 1.488483 Australian Dollar"
            },
            {
                "title": "1 AUD = 27.419394 UYU",
                "link": "http://www.floatrates.com/aud/uyu/",
                "description": "1 Australian Dollar = 27.419394 Uruguayan Peso",
                "pubDate": null,
                "baseCurrency": "AUD",
                "baseName": "Australian Dollar",
                "targetCurrency": "UYU",
                "targetName": "Uruguayan Peso",
                "exchangeRate": "27.419394",
                "inverseRate": "0.036471",
                "inverseDescription": "1 Uruguayan Peso = 0.036471 Australian Dollar"
            },
            {
                "title": "1 AUD = 8.741622 BWP",
                "link": "http://www.floatrates.com/aud/bwp/",
                "description": "1 Australian Dollar = 8.741622 Botswana Pula",
                "pubDate": null,
                "baseCurrency": "AUD",
                "baseName": "Australian Dollar",
                "targetCurrency": "BWP",
                "targetName": "Botswana Pula",
                "exchangeRate": "8.741622",
                "inverseRate": "0.114395",
                "inverseDescription": "1 Botswana Pula = 0.114395 Australian Dollar"
            },
            {
                "title": "1 AUD = 5.222694 GTQ",
                "link": "http://www.floatrates.com/aud/gtq/",
                "description": "1 Australian Dollar = 5.222694 Guatemalan Quetzal",
                "pubDate": null,
                "baseCurrency": "AUD",
                "baseName": "Australian Dollar",
                "targetCurrency": "GTQ",
                "targetName": "Guatemalan Quetzal",
                "exchangeRate": "5.222694",
                "inverseRate": "0.191472",
                "inverseDescription": "1 Guatemalan Quetzal = 0.191472 Australian Dollar"
            },
            {
                "title": "1 AUD = 28,253.517950 IRR",
                "link": "http://www.floatrates.com/aud/irr/",
                "description": "1 Australian Dollar = 28,253.517950 Iranian rial",
                "pubDate": null,
                "baseCurrency": "AUD",
                "baseName": "Australian Dollar",
                "targetCurrency": "IRR",
                "targetName": "Iranian rial",
                "exchangeRate": "28,253.517950",
                "inverseRate": "0.000035",
                "inverseDescription": "1 Iranian rial = 0.000035 Australian Dollar"
            },
            {
                "title": "1 AUD = 168.412765 YER",
                "link": "http://www.floatrates.com/aud/yer/",
                "description": "1 Australian Dollar = 168.412765 Yemeni rial",
                "pubDate": null,
                "baseCurrency": "AUD",
                "baseName": "Australian Dollar",
                "targetCurrency": "YER",
                "targetName": "Yemeni rial",
                "exchangeRate": "168.412765",
                "inverseRate": "0.005938",
                "inverseDescription": "1 Yemeni rial = 0.005938 Australian Dollar"
            },
            {
                "title": "1 AUD = 2,770.200258 KHR",
                "link": "http://www.floatrates.com/aud/khr/",
                "description": "1 Australian Dollar = 2,770.200258 Cambodian riel",
                "pubDate": null,
                "baseCurrency": "AUD",
                "baseName": "Australian Dollar",
                "targetCurrency": "KHR",
                "targetName": "Cambodian riel",
                "exchangeRate": "2,770.200258",
                "inverseRate": "0.000361",
                "inverseDescription": "1 Cambodian riel = 0.000361 Australian Dollar"
            },
            {
                "title": "1 AUD = 2.003895 BYN",
                "link": "http://www.floatrates.com/aud/byn/",
                "description": "1 Australian Dollar = 2.003895 Belarussian Ruble",
                "pubDate": null,
                "baseCurrency": "AUD",
                "baseName": "Australian Dollar",
                "targetCurrency": "BYN",
                "targetName": "Belarussian Ruble",
                "exchangeRate": "2.003895",
                "inverseRate": "0.499028",
                "inverseDescription": "1 Belarussian Ruble = 0.499028 Australian Dollar"
            },
            {
                "title": "1 AUD = 10.406286 MVR",
                "link": "http://www.floatrates.com/aud/mvr/",
                "description": "1 Australian Dollar = 10.406286 Maldivian rufiyaa",
                "pubDate": null,
                "baseCurrency": "AUD",
                "baseName": "Australian Dollar",
                "targetCurrency": "MVR",
                "targetName": "Maldivian rufiyaa",
                "exchangeRate": "10.406286",
                "inverseRate": "0.096096",
                "inverseDescription": "1 Maldivian rufiyaa = 0.096096 Australian Dollar"
            },
            {
                "title": "1 AUD = 29.600103 MUR",
                "link": "http://www.floatrates.com/aud/mur/",
                "description": "1 Australian Dollar = 29.600103 Mauritian Rupee",
                "pubDate": null,
                "baseCurrency": "AUD",
                "baseName": "Australian Dollar",
                "targetCurrency": "MUR",
                "targetName": "Mauritian Rupee",
                "exchangeRate": "29.600103",
                "inverseRate": "0.033784",
                "inverseDescription": "1 Mauritian Rupee = 0.033784 Australian Dollar"
            },
            {
                "title": "1 AUD = 8.835852 SCR",
                "link": "http://www.floatrates.com/aud/scr/",
                "description": "1 Australian Dollar = 8.835852 Seychelles rupee",
                "pubDate": null,
                "baseCurrency": "AUD",
                "baseName": "Australian Dollar",
                "targetCurrency": "SCR",
                "targetName": "Seychelles rupee",
                "exchangeRate": "8.835852",
                "inverseRate": "0.113175",
                "inverseDescription": "1 Seychelles rupee = 0.113175 Australian Dollar"
            },
            {
                "title": "1 AUD = 2.613438 PEN",
                "link": "http://www.floatrates.com/aud/pen/",
                "description": "1 Australian Dollar = 2.613438 Peruvian Nuevo Sol",
                "pubDate": null,
                "baseCurrency": "AUD",
                "baseName": "Australian Dollar",
                "targetCurrency": "PEN",
                "targetName": "Peruvian Nuevo Sol",
                "exchangeRate": "2.613438",
                "inverseRate": "0.382638",
                "inverseDescription": "1 Peruvian Nuevo Sol = 0.382638 Australian Dollar"
            },
            {
                "title": "1 AUD = 54.384227 KGS",
                "link": "http://www.floatrates.com/aud/kgs/",
                "description": "1 Australian Dollar = 54.384227 Kyrgyzstan Som",
                "pubDate": null,
                "baseCurrency": "AUD",
                "baseName": "Australian Dollar",
                "targetCurrency": "KGS",
                "targetName": "Kyrgyzstan Som",
                "exchangeRate": "54.384227",
                "inverseRate": "0.018388",
                "inverseDescription": "1 Kyrgyzstan Som = 0.018388 Australian Dollar"
            },
            {
                "title": "1 AUD = 6.853902 TJS",
                "link": "http://www.floatrates.com/aud/tjs/",
                "description": "1 Australian Dollar = 6.853902 Tajikistan Ruble",
                "pubDate": null,
                "baseCurrency": "AUD",
                "baseName": "Australian Dollar",
                "targetCurrency": "TJS",
                "targetName": "Tajikistan Ruble",
                "exchangeRate": "6.853902",
                "inverseRate": "0.145902",
                "inverseDescription": "1 Tajikistan Ruble = 0.145902 Australian Dollar"
            },
            {
                "title": "1 AUD = 7,363.000218 UZS",
                "link": "http://www.floatrates.com/aud/uzs/",
                "description": "1 Australian Dollar = 7,363.000218 Uzbekistan Sum",
                "pubDate": null,
                "baseCurrency": "AUD",
                "baseName": "Australian Dollar",
                "targetCurrency": "UZS",
                "targetName": "Uzbekistan Sum",
                "exchangeRate": "7,363.000218",
                "inverseRate": "0.000136",
                "inverseDescription": "1 Uzbekistan Sum = 0.000136 Australian Dollar"
            },
            {
                "title": "1 AUD = 80.999597 KES",
                "link": "http://www.floatrates.com/aud/kes/",
                "description": "1 Australian Dollar = 80.999597 Kenyan shilling",
                "pubDate": null,
                "baseCurrency": "AUD",
                "baseName": "Australian Dollar",
                "targetCurrency": "KES",
                "targetName": "Kenyan shilling",
                "exchangeRate": "80.999597",
                "inverseRate": "0.012346",
                "inverseDescription": "1 Kenyan shilling = 0.012346 Australian Dollar"
            },
            {
                "title": "1 AUD = 382.622513 SOS",
                "link": "http://www.floatrates.com/aud/sos/",
                "description": "1 Australian Dollar = 382.622513 Somali shilling",
                "pubDate": null,
                "baseCurrency": "AUD",
                "baseName": "Australian Dollar",
                "targetCurrency": "SOS",
                "targetName": "Somali shilling",
                "exchangeRate": "382.622513",
                "inverseRate": "0.002614",
                "inverseDescription": "1 Somali shilling = 0.002614 Australian Dollar"
            },
            {
                "title": "1 AUD = 1,569.372164 TZS",
                "link": "http://www.floatrates.com/aud/tzs/",
                "description": "1 Australian Dollar = 1,569.372164 Tanzanian shilling",
                "pubDate": null,
                "baseCurrency": "AUD",
                "baseName": "Australian Dollar",
                "targetCurrency": "TZS",
                "targetName": "Tanzanian shilling",
                "exchangeRate": "1,569.372164",
                "inverseRate": "0.000637",
                "inverseDescription": "1 Tanzanian shilling = 0.000637 Australian Dollar"
            },
            {
                "title": "1 AUD = 2,567.719758 UGX",
                "link": "http://www.floatrates.com/aud/ugx/",
                "description": "1 Australian Dollar = 2,567.719758 Ugandan shilling",
                "pubDate": null,
                "baseCurrency": "AUD",
                "baseName": "Australian Dollar",
                "targetCurrency": "UGX",
                "targetName": "Ugandan shilling",
                "exchangeRate": "2,567.719758",
                "inverseRate": "0.000389",
                "inverseDescription": "1 Ugandan shilling = 0.000389 Australian Dollar"
            },
            {
                "title": "1 AUD = 1.776895 WST",
                "link": "http://www.floatrates.com/aud/wst/",
                "description": "1 Australian Dollar = 1.776895 Samoan tala",
                "pubDate": null,
                "baseCurrency": "AUD",
                "baseName": "Australian Dollar",
                "targetCurrency": "WST",
                "targetName": "Samoan tala",
                "exchangeRate": "1.776895",
                "inverseRate": "0.562780",
                "inverseDescription": "1 Samoan tala = 0.562780 Australian Dollar"
            },
            {
                "title": "1 AUD = 318.854480 KZT",
                "link": "http://www.floatrates.com/aud/kzt/",
                "description": "1 Australian Dollar = 318.854480 Kazakhstani Tenge",
                "pubDate": null,
                "baseCurrency": "AUD",
                "baseName": "Australian Dollar",
                "targetCurrency": "KZT",
                "targetName": "Kazakhstani Tenge",
                "exchangeRate": "318.854480",
                "inverseRate": "0.003136",
                "inverseDescription": "1 Kazakhstani Tenge = 0.003136 Australian Dollar"
            },
            {
                "title": "1 AUD = 2,164.394785 MNT",
                "link": "http://www.floatrates.com/aud/mnt/",
                "description": "1 Australian Dollar = 2,164.394785 Mongolian togrog",
                "pubDate": null,
                "baseCurrency": "AUD",
                "baseName": "Australian Dollar",
                "targetCurrency": "MNT",
                "targetName": "Mongolian togrog",
                "exchangeRate": "2,164.394785",
                "inverseRate": "0.000462",
                "inverseDescription": "1 Mongolian togrog = 0.000462 Australian Dollar"
            },
            {
                "title": "1 AUD = 78.830447 VUV",
                "link": "http://www.floatrates.com/aud/vuv/",
                "description": "1 Australian Dollar = 78.830447 Vanuatu vatu",
                "pubDate": null,
                "baseCurrency": "AUD",
                "baseName": "Australian Dollar",
                "targetCurrency": "VUV",
                "targetName": "Vanuatu vatu",
                "exchangeRate": "78.830447",
                "inverseRate": "0.012685",
                "inverseDescription": "1 Vanuatu vatu = 0.012685 Australian Dollar"
            },
            {
                "title": "1 AUD = 1.329346 BAM",
                "link": "http://www.floatrates.com/aud/bam/",
                "description": "1 Australian Dollar = 1.329346 Bosnia and Herzegovina convertible mark",
                "pubDate": null,
                "baseCurrency": "AUD",
                "baseName": "Australian Dollar",
                "targetCurrency": "BAM",
                "targetName": "Bosnia and Herzegovina convertible mark",
                "exchangeRate": "1.329346",
                "inverseRate": "0.752250",
                "inverseDescription": "1 Bosnia and Herzegovina convertible mark = 0.752250 Australian Dollar"
            },
            {
                "title": "1 AUD = 3.211948 PLN",
                "link": "http://www.floatrates.com/aud/pln/",
                "description": "1 Australian Dollar = 3.211948 Polish Zloty",
                "pubDate": null,
                "baseCurrency": "AUD",
                "baseName": "Australian Dollar",
                "targetCurrency": "PLN",
                "targetName": "Polish Zloty",
                "exchangeRate": "3.211948",
                "inverseRate": "0.311338",
                "inverseDescription": "1 Polish Zloty = 0.311338 Australian Dollar"
            }
        ]
    }
}